{
  "resources": [
    {
      "path": "data.csv",
      "name": "data",
      "profile": "tabular-data-resource",
      "scheme": "file",
      "format": "csv",
      "hashing": "md5",
      "encoding": "utf-8",
      "schema": {
        "fields": [
          {
            "name": "Year",
            "type": "integer",
            "title": "Year"
          },
          {
            "name": "Sex of the petitioner",
            "type": "string",
            "constraints": {
              "enum": [
                "Men",
                "Women",
                ""
              ]
            },
            "title": "Sex of the petitioner"
          },
          {
            "name": "Criteria of discrimination",
            "type": "string",
            "constraints": {
              "enum": [
                "Opinion",
                "Disability",
                "Social origin",
                "Language",
                "Sex/gender",
                "HIV status",
                "Sexual orientation",
                "Religion/belief",
                "Professional status",
                "Civil status",
                "Political affiliation",
                "Place of residence",
                "Ethnical affiliation",
                "Maternity",
                "Nationality",
                "Age",
                "Race",
                "Trade-union activity",
                "Pensioner status",
                "Other",
                ""
              ]
            },
            "title": "Criteria of discrimination"
          },
          {
            "name": "Area of discrimination",
            "type": "string",
            "constraints": {
              "enum": [
                "Discrimination on the labour market",
                "Access to education",
                "Access to goods and services available to the public",
                "Access to justice",
                "Hate speech",
                "Injured human dignity",
                "Exercing parental rights",
                "Other",
                ""
              ]
            },
            "title": "Area of discrimination"
          },
          {
            "name": "Form of discrimination",
            "type": "string",
            "constraints": {
              "enum": [
                "Direct",
                "Indirect",
                "By association",
                "Instigation to discrimination",
                "Harassment",
                "Victimization",
                "Refuse of reasonable accommodation",
                "Racial segregation",
                ""
              ]
            },
            "title": "Form of discrimination"
          },
          {
            "name": "Area of residence",
            "type": "string",
            "constraints": {
              "enum": [
                "Urban",
                "Rural",
                ""
              ]
            },
            "title": "Area of residence"
          },
          {
            "name": "Value",
            "type": "number",
            "title": "Value"
          }
        ]
      }
    }
  ],
  "profile": "data-package",
  "name": "10-3-1-1",
  "title": "global_indicators.10-3-1-1-title"
}