{
  "resources": [
    {
      "path": "data.csv",
      "name": "data",
      "profile": "tabular-data-resource",
      "scheme": "file",
      "format": "csv",
      "hashing": "md5",
      "encoding": "utf-8",
      "schema": {
        "fields": [
          {
            "name": "Year",
            "type": "number",
            "title": "Anul"
          },
          {
            "name": "Value",
            "type": "number",
            "title": "Value"
          }
        ]
      }
    }
  ],
  "profile": "data-package",
  "name": "17-19-2",
  "title": "Ponderea țărilor care (a) au efectuat cel puțin un recensământ al populației și al locuințelor în ultimii 10 ani; și (b) au atins rata înregistrării a nașterilor de 100% și deceselor de 80%"
}