{"data":{"Year":[2010,2010,2010,2010,2010,2010,2010,2010,2010,2010,2010,2010,2010,2010,2010,2010,2010,2010,2010,2010,2011,2011,2011,2011,2011,2011,2011,2011,2011,2011,2011,2011,2011,2011,2011,2011,2011,2011,2011,2011,2012,2012,2012,2012,2012,2012,2012,2012,2012,2012,2012,2012,2012,2012,2012,2012,2012,2012,2012,2012,2013,2013,2013,2013,2013,2013,2013,2013,2013,2013,2013,2013,2013,2013,2013,2013,2013,2013,2013,2013,2014,2014,2014,2014,2014,2014,2014,2014,2014,2014,2014,2014,2014,2014,2014,2014,2014,2014,2014,2014,2015,2015,2015,2015,2015,2015,2015,2015,2015,2015,2015,2015,2015,2015,2015,2015,2015,2015,2015,2015,2016,2016,2016,2016,2016,2016,2016,2016,2016,2016,2016,2016,2016,2016,2016,2016,2016,2016,2016,2016,2017,2017,2017,2017,2017,2017,2017,2017,2017,2017,2017,2017,2017,2017,2017,2017,2017,2017,2017,2017,2018,2018,2018,2018,2018,2018,2018,2018,2018,2018,2018,2018,2018,2018,2018,2018,2018,2018,2018,2018,2019,2019,2019,2019,2019,2019,2019,2019,2019,2019,2019,2019,2019,2019,2019,2019,2019,2019,2019,2019,2020,2020,2020,2020,2020,2020,2020,2020,2020,2020,2020,2020,2020,2020,2020,2020,2020,2020,2020,2020,2021,2021,2021,2021,2021,2021,2021,2021,2021,2021,2021,2021,2021,2021,2021,2021,2021,2021,2021,2021,2022,2022,2022,2022,2022,2022,2022,2022,2022,2022,2022,2022,2022,2022,2022,2022,2022,2022,2022,2022],"Reported on a person, by sources":[null,"Auto","Feroviar","Aerian",null,null,null,null,null,null,null,null,null,null,null,null,null,null,null,null,null,"Auto","Feroviar","Aerian",null,null,null,null,null,null,null,null,null,null,null,null,null,null,null,null,null,"Auto","Feroviar","Aerian",null,null,null,null,null,null,null,null,null,null,null,null,null,null,null,null,null,"Auto","Feroviar","Aerian",null,null,null,null,null,null,null,null,null,null,null,null,null,null,null,null,null,"Auto","Feroviar","Aerian",null,null,null,null,null,null,null,null,null,null,null,null,null,null,null,null,null,"Auto","Feroviar","Aerian",null,null,null,null,null,null,null,null,null,null,null,null,null,null,null,null,null,"Auto","Feroviar","Aerian",null,null,null,null,null,null,null,null,null,null,null,null,null,null,null,null,null,"Auto","Feroviar","Aerian",null,null,null,null,null,null,null,null,null,null,null,null,null,null,null,null,null,"Auto","Feroviar","Aerian",null,null,null,null,null,null,null,null,null,null,null,null,null,null,null,null,null,"Auto","Feroviar","Aerian",null,null,null,null,null,null,null,null,null,null,null,null,null,null,null,null,null,"Auto","Feroviar","Aerian",null,null,null,null,null,null,null,null,null,null,null,null,null,null,null,null,null,"Auto","Feroviar","Aerian",null,null,null,null,null,null,null,null,null,null,null,null,null,null,null,null,null,"Auto","Feroviar","Aerian",null,null,null,null,null,null,null,null,null,null,null,null,null,null,null,null],"Reported on a person, by ingredients":[null,null,null,null,"Oxid de carbon","Dioxid de azot","Dioxid de sulf","Hidrocarburi","Aldehydes","Substan\u021be solide",null,null,null,null,null,null,null,null,null,null,null,null,null,null,"Oxid de carbon","Dioxid de azot","Dioxid de sulf","Hidrocarburi","Aldehydes","Substan\u021be solide",null,null,null,null,null,null,null,null,null,null,null,null,null,null,"Oxid de carbon","Dioxid de azot","Dioxid de sulf","Hidrocarburi","Aldehydes","Substan\u021be solide",null,null,null,null,null,null,null,null,null,null,null,null,null,null,"Oxid de carbon","Dioxid de azot","Dioxid de sulf","Hidrocarburi","Aldehydes","Substan\u021be solide",null,null,null,null,null,null,null,null,null,null,null,null,null,null,"Oxid de carbon","Dioxid de azot","Dioxid de sulf","Hidrocarburi","Aldehydes","Substan\u021be solide",null,null,null,null,null,null,null,null,null,null,null,null,null,null,"Oxid de carbon","Dioxid de azot","Dioxid de sulf","Hidrocarburi","Aldehydes","Substan\u021be solide",null,null,null,null,null,null,null,null,null,null,null,null,null,null,"Oxid de carbon","Dioxid de azot","Dioxid de sulf","Hidrocarburi","Aldehydes","Substan\u021be solide",null,null,null,null,null,null,null,null,null,null,null,null,null,null,"Oxid de carbon","Dioxid de azot","Dioxid de sulf","Hidrocarburi","Aldehydes","Substan\u021be solide",null,null,null,null,null,null,null,null,null,null,null,null,null,null,"Oxid de carbon","Dioxid de azot","Dioxid de sulf","Hidrocarburi","Aldehydes","Substan\u021be solide",null,null,null,null,null,null,null,null,null,null,null,null,null,null,"Oxid de carbon","Dioxid de azot","Dioxid de sulf","Hidrocarburi","Aldehydes","Substan\u021be solide",null,null,null,null,null,null,null,null,null,null,null,null,null,null,"Oxid de carbon","Dioxid de azot","Dioxid de sulf","Hidrocarburi","Aldehydes","Substan\u021be solide",null,null,null,null,null,null,null,null,null,null,null,null,null,null,"Oxid de carbon","Dioxid de azot","Dioxid de sulf","Hidrocarburi","Aldehydes","Substan\u021be solide",null,null,null,null,null,null,null,null,null,null,null,null,null,null,"Oxid de carbon","Dioxid de azot","Dioxid de sulf","Hidrocarburi","Aldehydes","Substan\u021be solide",null,null,null,null,null,null,null,null,null,null],"Quantity of emissions, total":[null,null,null,null,null,null,null,null,null,null,"Total",null,null,null,null,null,null,null,null,null,null,null,null,null,null,null,null,null,null,null,"Total",null,null,null,null,null,null,null,null,null,null,null,null,null,null,null,null,null,null,null,"Total",null,null,null,null,null,null,null,null,null,null,null,null,null,null,null,null,null,null,null,"Total",null,null,null,null,null,null,null,null,null,null,null,null,null,null,null,null,null,null,null,"Total",null,null,null,null,null,null,null,null,null,null,null,null,null,null,null,null,null,null,null,"Total",null,null,null,null,null,null,null,null,null,null,null,null,null,null,null,null,null,null,null,"Total",null,null,null,null,null,null,null,null,null,null,null,null,null,null,null,null,null,null,null,"Total",null,null,null,null,null,null,null,null,null,null,null,null,null,null,null,null,null,null,null,"Total",null,null,null,null,null,null,null,null,null,null,null,null,null,null,null,null,null,null,null,"Total",null,null,null,null,null,null,null,null,null,null,null,null,null,null,null,null,null,null,null,"Total",null,null,null,null,null,null,null,null,null,null,null,null,null,null,null,null,null,null,null,"Total",null,null,null,null,null,null,null,null,null,null,null,null,null,null,null,null,null,null,null,"Total",null,null,null,null,null,null,null,null,null],"Quantity of emissions, by sources":[null,null,null,null,null,null,null,null,null,null,null,"Auto","Feroviar","Aerian",null,null,null,null,null,null,null,null,null,null,null,null,null,null,null,null,null,"Auto","Feroviar","Aerian",null,null,null,null,null,null,null,null,null,null,null,null,null,null,null,null,null,"Auto","Feroviar","Aerian",null,null,null,null,null,null,null,null,null,null,null,null,null,null,null,null,null,"Auto","Feroviar","Aerian",null,null,null,null,null,null,null,null,null,null,null,null,null,null,null,null,null,"Auto","Feroviar","Aerian",null,null,null,null,null,null,null,null,null,null,null,null,null,null,null,null,null,"Auto","Feroviar","Aerian",null,null,null,null,null,null,null,null,null,null,null,null,null,null,null,null,null,"Auto","Feroviar","Aerian",null,null,null,null,null,null,null,null,null,null,null,null,null,null,null,null,null,"Auto","Feroviar","Aerian",null,null,null,null,null,null,null,null,null,null,null,null,null,null,null,null,null,"Auto","Feroviar","Aerian",null,null,null,null,null,null,null,null,null,null,null,null,null,null,null,null,null,"Auto","Feroviar","Aerian",null,null,null,null,null,null,null,null,null,null,null,null,null,null,null,null,null,"Auto","Feroviar","Aerian",null,null,null,null,null,null,null,null,null,null,null,null,null,null,null,null,null,"Auto","Feroviar","Aerian",null,null,null,null,null,null,null,null,null,null,null,null,null,null,null,null,null,"Auto","Feroviar","Aerian",null,null,null,null,null,null],"Quantity of emissions, by ingredients":[null,null,null,null,null,null,null,null,null,null,null,null,null,null,"Oxid de carbon","Dioxid de azot","Dioxid de sulf","Hidrocarburi","Aldehydes","Substan\u021be solide",null,null,null,null,null,null,null,null,null,null,null,null,null,null,"Oxid de carbon","Dioxid de azot","Dioxid de sulf","Hidrocarburi","Aldehydes","Substan\u021be solide",null,null,null,null,null,null,null,null,null,null,null,null,null,null,"Oxid de carbon","Dioxid de azot","Dioxid de sulf","Hidrocarburi","Aldehydes","Substan\u021be solide",null,null,null,null,null,null,null,null,null,null,null,null,null,null,"Oxid de carbon","Dioxid de azot","Dioxid de sulf","Hidrocarburi","Aldehydes","Substan\u021be solide",null,null,null,null,null,null,null,null,null,null,null,null,null,null,"Oxid de carbon","Dioxid de azot","Dioxid de sulf","Hidrocarburi","Aldehydes","Substan\u021be solide",null,null,null,null,null,null,null,null,null,null,null,null,null,null,"Oxid de carbon","Dioxid de azot","Dioxid de sulf","Hidrocarburi","Aldehydes","Substan\u021be solide",null,null,null,null,null,null,null,null,null,null,null,null,null,null,"Oxid de carbon","Dioxid de azot","Dioxid de sulf","Hidrocarburi","Aldehydes","Substan\u021be solide",null,null,null,null,null,null,null,null,null,null,null,null,null,null,"Oxid de carbon","Dioxid de azot","Dioxid de sulf","Hidrocarburi","Aldehydes","Substan\u021be solide",null,null,null,null,null,null,null,null,null,null,null,null,null,null,"Oxid de carbon","Dioxid de azot","Dioxid de sulf","Hidrocarburi","Aldehydes","Substan\u021be solide",null,null,null,null,null,null,null,null,null,null,null,null,null,null,"Oxid de carbon","Dioxid de azot","Dioxid de sulf","Hidrocarburi","Aldehydes","Substan\u021be solide",null,null,null,null,null,null,null,null,null,null,null,null,null,null,"Oxid de carbon","Dioxid de azot","Dioxid de sulf","Hidrocarburi","Aldehydes","Substan\u021be solide",null,null,null,null,null,null,null,null,null,null,null,null,null,null,"Oxid de carbon","Dioxid de azot","Dioxid de sulf","Hidrocarburi","Aldehydes","Substan\u021be solide",null,null,null,null,null,null,null,null,null,null,null,null,null,null,"Oxid de carbon","Dioxid de azot","Dioxid de sulf","Hidrocarburi","Aldehydes","Substan\u021be solide"],"Value":[null,null,null,null,null,null,null,null,null,null,154.8,146.5,1.6,6.7,109.2,15.8,3.9,15.0,8.3,2.6,null,null,null,null,null,null,null,null,null,null,188.7,174.8,4.0,9.9,134.7,18.4,4.5,21.0,7.4,2.7,null,null,null,null,null,null,null,null,null,null,154.2,140.1,2.7,11.4,118.3,14.3,3.3,15.1,1.0,2.0,null,null,null,null,null,null,null,null,null,null,226.6,213.1,2.8,10.7,165.1,24.9,6.7,24.2,1.7,4.0,68.0,62.6,0.9,4.5,52.2,5.6,1.2,7.8,0.3,0.9,194.3,179.0,2.7,12.6,149.2,16.0,3.5,22.4,1.0,2.2,68.5,63.1,1.0,4.4,52.6,5.6,1.2,7.9,0.4,0.8,194.3,178.9,2.7,12.6,149.2,16.0,3.5,22.4,1.0,2.2,71.9,59.2,1.0,11.7,51.7,7.1,1.8,7.7,2.5,1.1,201.5,166.0,2.9,32.6,144.8,19.8,5.1,21.6,7.0,3.2,117.0,107.4,0.9,8.7,89.7,10.9,2.5,11.6,0.7,1.6,322.3,296.0,2.4,23.9,247.1,29.9,7.0,31.9,2.0,4.4,84.2,73.2,0.7,10.3,61.7,9.2,2.4,8.6,0.7,1.6,227.9,198.1,2.0,27.8,167.1,25.0,6.6,23.3,1.8,4.1,71.1,61.5,0.3,9.3,48.0,9.9,3.0,7.7,0.8,1.7,189.5,163.8,0.9,24.8,127.8,26.5,7.9,20.5,2.0,4.8,59.0,56.3,0.3,2.4,38.2,9.0,2.8,6.6,0.7,1.7,155.6,148.7,0.7,6.2,100.6,23.9,7.4,17.3,1.8,4.6,74.0,65.8,0.3,7.9,49.8,10.4,3.0,8.1,0.8,1.9,193.4,172.1,0.7,20.6,130.3,27.2,7.9,21.1,2.0,4.9,null,null,null,null,null,null,null,null,null,null,null,null,null,null,null,null,null,null,null,null]},"edges":[]}