{
  "resources": [
    {
      "path": "data.csv",
      "name": "data",
      "profile": "tabular-data-resource",
      "scheme": "file",
      "format": "csv",
      "hashing": "md5",
      "encoding": "utf-8",
      "schema": {
        "fields": [
          {
            "name": "Year",
            "type": "integer",
            "title": "Anul"
          },
          {
            "name": "Sex",
            "type": "string",
            "constraints": {
              "enum": [
                "Bărbați",
                "Femei",
                ""
              ]
            },
            "title": "Sex"
          },
          {
            "name": "Nivel de instruire",
            "type": "string",
            "constraints": {
              "enum": [
                "Secundare",
                "Mediu de specialitate",
                "Superior",
                ""
              ]
            },
            "title": "Nivel de instruire"
          },
          {
            "name": "Institutions where have been made payments",
            "type": "string",
            "constraints": {
              "enum": [
                "Inspectoratele fiscale",
                "Vama",
                "Poliția",
                "Procuratura",
                "Inspecțiile sanitar-epidemiologice",
                "Birourile/serviciile cadastrale",
                "Instanțele de judecată",
                "Achizițiile publice",
                "Înregistrarea transportului și eliberarea permisului de conducere",
                "Revizia tehnică a automobilelor",
                "Eliberarea autorizațiilor de construcție",
                "Inspecția muncii",
                ""
              ]
            },
            "title": "Instituțiile unde s-au efectuat plăți"
          },
          {
            "name": "Value",
            "type": "number",
            "title": "Value"
          }
        ]
      }
    }
  ],
  "profile": "data-package",
  "name": "16-5-2",
  "title": "Ponderea antreprenorilor care au avut cel puțin un contact cu un funcționar public și care au plătit mită unui funcționar public sau au fost rugați să plătească mită de către acești funcționari publici în ultimele 12 luni"
}