{
  "resources": [
    {
      "path": "data.csv",
      "name": "data",
      "profile": "tabular-data-resource",
      "scheme": "file",
      "format": "csv",
      "hashing": "md5",
      "encoding": "utf-8",
      "schema": {
        "fields": [
          {
            "name": "Year",
            "type": "integer",
            "title": "Anul"
          },
          {
            "name": "Sex",
            "type": "string",
            "constraints": {
              "enum": [
                "Bărbați",
                "Femei",
                ""
              ]
            },
            "title": "Sex"
          },
          {
            "name": "Area of residence",
            "type": "string",
            "constraints": {
              "enum": [
                "Urban",
                "Rural",
                ""
              ]
            },
            "title": "Mediul de reședință"
          },
          {
            "name": "Area of residence/Sex",
            "type": "string",
            "constraints": {
              "enum": [
                "Urban/Bărbați",
                "Rural/men",
                "Urban/Femei",
                "Rural/Femei",
                ""
              ]
            },
            "title": "Mediul de reședință/Sex"
          },
          {
            "name": "Age group/sex",
            "type": "string",
            "constraints": {
              "enum": [
                "15-24/Bărbați",
                "15-24/ Women",
                "25-34/Bărbați",
                "25-34/Femei",
                "35-44/Bărbați",
                "35-44/Femei",
                "45-49/Bărbați",
                "45-49/Femei",
                ""
              ]
            },
            "title": "Age group/sex"
          },
          {
            "name": "Value",
            "type": "number",
            "title": "Value"
          }
        ]
      }
    }
  ],
  "profile": "data-package",
  "name": "3-5-2-1",
  "title": "Prevalența consumului nociv de alcool"
}